{
  "attributes": [
    {
      "allow_nil?": false,
      "default": "nil",
      "generated?": true,
      "precision": null,
      "primary_key?": true,
      "references": null,
      "scale": null,
      "size": null,
      "source": "id",
      "type": "bigint"
    },
    {
      "allow_nil?": true,
      "default": "nil",
      "generated?": false,
      "precision": null,
      "primary_key?": false,
      "references": null,
      "scale": null,
      "size": null,
      "source": "body",
      "type": "text"
    },
    {
      "allow_nil?": false,
      "default": "false",
      "generated?": false,
      "precision": null,
      "primary_key?": false,
      "references": null,
      "scale": null,
      "size": null,
      "source": "received",
      "type": "boolean"
    },
    {
      "allow_nil?": false,
      "default": "\"system_notification\"",
      "generated?": false,
      "precision": null,
      "primary_key?": false,
      "references": null,
      "scale": null,
      "size": null,
      "source": "type",
      "type": "text"
    },
    {
      "allow_nil?": false,
      "default": "fragment(\"gen_random_uuid()\")",
      "generated?": false,
      "precision": null,
      "primary_key?": false,
      "references": null,
      "scale": null,
      "size": null,
      "source": "message_group_id",
      "type": "uuid"
    },
    {
      "allow_nil?": false,
      "default": "fragment(\"(now() AT TIME ZONE 'utc')\")",
      "generated?": false,
      "precision": null,
      "primary_key?": false,
      "references": null,
      "scale": null,
      "size": null,
      "source": "inserted_at",
      "type": "utc_datetime_usec"
    },
    {
      "allow_nil?": false,
      "default": "fragment(\"(now() AT TIME ZONE 'utc')\")",
      "generated?": false,
      "precision": null,
      "primary_key?": false,
      "references": null,
      "scale": null,
      "size": null,
      "source": "updated_at",
      "type": "utc_datetime_usec"
    },
    {
      "allow_nil?": true,
      "default": "nil",
      "generated?": false,
      "precision": null,
      "primary_key?": false,
      "references": {
        "deferrable": false,
        "destination_attribute": "id",
        "destination_attribute_default": null,
        "destination_attribute_generated": null,
        "index?": false,
        "match_type": null,
        "match_with": null,
        "multitenancy": {
          "attribute": null,
          "global": null,
          "strategy": null
        },
        "name": "user_messages_sender_id_fkey",
        "on_delete": null,
        "on_update": null,
        "primary_key?": true,
        "schema": "public",
        "table": "users"
      },
      "scale": null,
      "size": null,
      "source": "sender_id",
      "type": "bigint"
    },
    {
      "allow_nil?": false,
      "default": "nil",
      "generated?": false,
      "precision": null,
      "primary_key?": false,
      "references": {
        "deferrable": false,
        "destination_attribute": "id",
        "destination_attribute_default": null,
        "destination_attribute_generated": null,
        "index?": false,
        "match_type": null,
        "match_with": null,
        "multitenancy": {
          "attribute": null,
          "global": null,
          "strategy": null
        },
        "name": "user_messages_recipient_id_fkey",
        "on_delete": null,
        "on_update": null,
        "primary_key?": true,
        "schema": "public",
        "table": "users"
      },
      "scale": null,
      "size": null,
      "source": "recipient_id",
      "type": "bigint"
    },
    {
      "allow_nil?": true,
      "default": "nil",
      "generated?": false,
      "precision": null,
      "primary_key?": false,
      "references": {
        "deferrable": false,
        "destination_attribute": "id",
        "destination_attribute_default": null,
        "destination_attribute_generated": null,
        "index?": false,
        "match_type": null,
        "match_with": null,
        "multitenancy": {
          "attribute": null,
          "global": null,
          "strategy": null
        },
        "name": "user_messages_shared_video_id_fkey",
        "on_delete": null,
        "on_update": null,
        "primary_key?": true,
        "schema": "public",
        "table": "videos"
      },
      "scale": null,
      "size": null,
      "source": "shared_video_id",
      "type": "bigint"
    }
  ],
  "base_filter": null,
  "check_constraints": [],
  "custom_indexes": [],
  "custom_statements": [],
  "has_create_action": true,
  "hash": "49988C6598A35FC5DE84CCF2A6182F22E3AAB9316D6B3D058573A1665FBDF4EB",
  "identities": [],
  "multitenancy": {
    "attribute": null,
    "global": null,
    "strategy": null
  },
  "repo": "Elixir.FosBjj.Repo",
  "schema": null,
  "table": "user_messages"
}